odoo/addons/project_milestone_tree/README.rst
odoo/addons/project_milestone_tree/__init__.py
odoo/addons/project_milestone_tree/__manifest__.py
odoo/addons/project_milestone_tree/i18n/it.po
odoo/addons/project_milestone_tree/i18n/project_milestone_tree.pot
odoo/addons/project_milestone_tree/readme/DESCRIPTION.rst
odoo/addons/project_milestone_tree/static/description/icon.png
odoo/addons/project_milestone_tree/static/description/index.html
odoo/addons/project_milestone_tree/views/project_milestone.xml
odoo_addon_project_milestone_tree-16.0.1.0.0.3.dist-info/METADATA
odoo_addon_project_milestone_tree-16.0.1.0.0.3.dist-info/WHEEL
odoo_addon_project_milestone_tree-16.0.1.0.0.3.dist-info/top_level.txt
odoo_addon_project_milestone_tree-16.0.1.0.0.3.dist-info/RECORD
